AUTHORS
ChangeLog
LICENSE
README.rst
requirements.txt
setup.cfg
setup.py
test-requirements.txt
tox.ini
falcon_hateoas/__init__.py
falcon_hateoas/decorators.py
falcon_hateoas/middleware.py
falcon_hateoas/resources.py
falcon_hateoas.egg-info/PKG-INFO
falcon_hateoas.egg-info/SOURCES.txt
falcon_hateoas.egg-info/dependency_links.txt
falcon_hateoas.egg-info/not-zip-safe
falcon_hateoas.egg-info/pbr.json
falcon_hateoas.egg-info/requires.txt
falcon_hateoas.egg-info/top_level.txt
tests/__init__.py
tests/test_middleware.py
tests/test_resources.py