Metadata-Version: 1.1
Name: falcon-hateoas
Version: 0.1.0
Summary: HATEOAS REST API for Falcon Framework
Home-page: UNKNOWN
Author: VNET a.s.
Author-email: UNKNOWN
License: MIT
Platform: UNKNOWN
Classifier: Intended Audience :: Developers
Classifier: Programming Language :: Python :: 3
Classifier: Topic :: Internet :: WWW/HTTP
